mypykit/__init__.py
mypykit/common/__init__.py
mypykit/common/constants.py
mypykit/stock/__init__.py
mypykit/stock/listup.py
mypykit-0.0.3.dist-info/LICENSE.txt
mypykit-0.0.3.dist-info/METADATA
mypykit-0.0.3.dist-info/WHEEL
mypykit-0.0.3.dist-info/top_level.txt
mypykit-0.0.3.dist-info/RECORD
