Metadata-Version: 2.1
Name: mypykit
Version: 0.0.3
Summary: my sample lib
Author: haninam
Author-email: 2050love@naver.com
Classifier: Programming Language :: Python :: 3
Requires-Python: >=3.6
License-File: LICENSE.txt
Requires-Dist: pykrx
Requires-Dist: pandas
